exp07/full_adder.sv
module full_adder (
    input  logic A,
    input  logic B,
    input  logic Cin,
    output logic Sum,
    output logic Cout
);

    assign Sum  = A ^ B ^ Cin;
    assign Cout = (A & B) | (B & Cin) | (A & Cin);

endmodule

exp07/half_adder.sv
module half_adder (
    input  logic A,
    input  logic B,
    output logic Sum,
    output logic Carry
);

    assign Sum   = A ^ B;
    assign Carry = A & B;

endmodule

exp07/tb.sv
`timescale 1ns/1ps

module tb;

    logic A, B, Cin;

    logic HA_Sum, HA_Carry;
    logic FA_Sum, FA_Cout;

    // Half Adder
    half_adder HA (
        .A(A),
        .B(B),
        .Sum(HA_Sum),
        .Carry(HA_Carry)
    );

    // Full Adder
    full_adder FA (
        .A(A),
        .B(B),
        .Cin(Cin),
        .Sum(FA_Sum),
        .Cout(FA_Cout)
    );

    initial begin

        // Generate waveform
        $dumpfile("wave.vcd");
        $dumpvars(0, tb);

        // -------------------------
        // HALF ADDER
        // -------------------------

        $display("\nHALF ADDER");

        A = 0; B = 0;
        #10;
        $display("A=%b B=%b Sum=%b Carry=%b",
                 A, B, HA_Sum, HA_Carry);

        A = 0; B = 1;
        #10;
        $display("A=%b B=%b Sum=%b Carry=%b",
                 A, B, HA_Sum, HA_Carry);

        A = 1; B = 0;
        #10;
        $display("A=%b B=%b Sum=%b Carry=%b",
                 A, B, HA_Sum, HA_Carry);

        A = 1; B = 1;
        #10;
        $display("A=%b B=%b Sum=%b Carry=%b",
                 A, B, HA_Sum, HA_Carry);


        // -------------------------
        // FULL ADDER
        // -------------------------

        $display("\nFULL ADDER");

        A = 0; B = 0; Cin = 0;
        #10;
        $display("A=%b B=%b Cin=%b Sum=%b Cout=%b",
                 A, B, Cin, FA_Sum, FA_Cout);

        A = 0; B = 0; Cin = 1;
        #10;
        $display("A=%b B=%b Cin=%b Sum=%b Cout=%b",
                 A, B, Cin, FA_Sum, FA_Cout);

        A = 0; B = 1; Cin = 0;
        #10;
        $display("A=%b B=%b Cin=%b Sum=%b Cout=%b",
                 A, B, Cin, FA_Sum, FA_Cout);

        A = 0; B = 1; Cin = 1;
        #10;
        $display("A=%b B=%b Cin=%b Sum=%b Cout=%b",
                 A, B, Cin, FA_Sum, FA_Cout);

        A = 1; B = 0; Cin = 0;
        #10;
        $display("A=%b B=%b Cin=%b Sum=%b Cout=%b",
                 A, B, Cin, FA_Sum, FA_Cout);

        A = 1; B = 0; Cin = 1;
        #10;
        $display("A=%b B=%b Cin=%b Sum=%b Cout=%b",
                 A, B, Cin, FA_Sum, FA_Cout);

        A = 1; B = 1; Cin = 0;
        #10;
        $display("A=%b B=%b Cin=%b Sum=%b Cout=%b",
                 A, B, Cin, FA_Sum, FA_Cout);

        A = 1; B = 1; Cin = 1;
        #10;
        $display("A=%b B=%b Cin=%b Sum=%b Cout=%b",
                 A, B, Cin, FA_Sum, FA_Cout);

        $finish;

    end

endmodule

exp07/wave.vcd
$version Generated by VerilatedVcd $end
$timescale 1ps $end
 $scope module tb $end
  $var wire 1 " A $end
  $var wire 1 # B $end
  $var wire 1 $ Cin $end
  $var wire 1 % HA_Sum $end
  $var wire 1 & HA_Carry $end
  $var wire 1 ' FA_Sum $end
  $var wire 1 ( FA_Cout $end
  $scope module FA $end
   $var wire 1 " A $end
   $var wire 1 # B $end
   $var wire 1 $ Cin $end
   $var wire 1 ' Sum $end
   $var wire 1 ( Cout $end
  $upscope $end
  $scope module HA $end
   $var wire 1 " A $end
   $var wire 1 # B $end
   $var wire 1 % Sum $end
   $var wire 1 & Carry $end
  $upscope $end
 $upscope $end
$enddefinitions $end


#0
0"
0#
0$
0%
0&
0'
0(
#10000
1#
1%
1'
#20000
1"
0#
#30000
1#
0%
1&
0'
1(
#40000
0"
0#
0&
0(
#50000
1$
1'
#60000
1#
0$
1%
#70000
1$
0'
1(
#80000
1"
0#
0$
1'
0(
#90000
1$
0'
1(
#100000
1#
0$
0%
1&
#110000
1$
1'
